[
 {
   "prezime1": "Дабарчић",
   "prezime2": "Дабесковић",
   "prezime3": "Дабетић",
   "prezime4": "Дабижљевић",
   "prezime5": "Дабић",
   "prezime6": "Дабовић",
   "prezime7": "Дабуловић",
   "prezime8": "Давидов",
   "prezime9": "Давидовац",
   "prezime10": "Давидовић",
   "prezime11": "Давинић",
   "prezime12": "Даговић",
   "prezime13": "Дадић",
   "prezime14": "Даишевић",
   "prezime15": "Дајић",
   "prezime16": "Дајлић",
   "prezime17": "Дајовић",
   "prezime18": "Дакић",
   "prezime19": "Даковић",
   "prezime20": "Даљевић",
   "prezime21": "Дамјанац",
   "prezime22": "Дамјанић",
   "prezime23": "Дамјанов",
   "prezime24": "Дамјановић",
   "prezime25": "Дамјанчевић",
   "prezime26": "Дамљановић",
   "prezime27": "Дамњанац",
   "prezime28": "Дамњановић",
   "prezime29": "Дамчевић",
   "prezime30": "Дангић",
   "prezime31": "Дангубић",
   "prezime32": "Данилов",
   "prezime33": "Даниловац",
   "prezime34": "Даниловић",
   "prezime35": "Даничић",
   "prezime36": "Данков",
   "prezime37": "Данковић",
   "prezime38": "Данкулов",
   "prezime39": "Данојевић",
   "prezime40": "Данојлић",
   "prezime41": "Данојловић",
   "prezime42": "Данчевић",
   "prezime43": "Данчеловић",
   "prezime44": "Данчетовић",
   "prezime45": "Данчула",
   "prezime46": "Данчуловић",
   "prezime47": "Данчуо",
   "prezime48": "Дапчевић",
   "prezime49": "Дардић",
   "prezime50": "Даријевић",
   "prezime51": "Даскаловић",
   "prezime52": "Даћевац",
   "prezime53": "Дафунић",
   "prezime54": "Дацић",
   "prezime55": "Дацковић",
   "prezime56": "Дацовић",
   "prezime57": "Дачевић",
   "prezime58": "Дачић",
   "prezime59": "Дачковић",
   "prezime60": "Дачовић",
   "prezime61": "Дашковић",
   "prezime62": "Двизац",
   "prezime63": "Двокић",
   "prezime64": "Дворанац",
   "prezime65": "Дворанчић",
   "prezime66": "Дворнић",
   "prezime67": "Дебелногић",
   "prezime68": "Дебељак",
   "prezime69": "Дебељаковић",
   "prezime70": "Дебељачки",
   "prezime71": "Дебељевић",
   "prezime72": "Дебељковић",
   "prezime73": "Дебљовић",
   "prezime74": "Деветак",
   "prezime75": "Девеџић",
   "prezime76": "Деврња",
   "prezime77": "Дегориција",
   "prezime78": "Дедеић",
   "prezime79": "Дедејић",
   "prezime80": "Дедијер",
   "prezime81": "Дедић",
   "prezime82": "Дедовић",
   "prezime83": "Деђански",
   "prezime84": "Дејанић",
   "prezime85": "Дејановић",
   "prezime86": "Дејковић",
   "prezime87": "Дејовић",
   "prezime88": "Делевић",
   "prezime89": "Делибашић",
   "prezime90": "Делиблаћанин",
   "prezime91": "Делић",
   "prezime92": "Дељанин",
   "prezime93": "Демић",
   "prezime94": "Демоња",
   "prezime95": "Демоњић",
   "prezime96": "Денда",
   "prezime97": "Денић",
   "prezime98": "Денкић",
   "prezime99": "Денковић",
   "prezime100": "Деновић",
   "prezime101": "Денчић",
   "prezime102": "Дерајић",
   "prezime103": "Дерета",
   "prezime104": "Деретић",
   "prezime105": "Дерикоњић",
   "prezime106": "Дерикрава",
   "prezime107": "Дерикучка",
   "prezime108": "Дероко",
   "prezime109": "Дероњић",
   "prezime110": "Десанчић",
   "prezime111": "Десивојевић",
   "prezime112": "Десимировић",
   "prezime113": "Десница",
   "prezime114": "Десовић",
   "prezime115": "Деспенић",
   "prezime116": "Деспинић",
   "prezime117": "Деспић",
   "prezime118": "Деспот",
   "prezime119": "Деспотов",
   "prezime120": "Деспотовић",
   "prezime121": "Деура",
   "prezime122": "Деурић",
   "prezime123": "Дешић",
   "prezime124": "Дивац",
   "prezime125": "Дивић",
   "prezime126": "Дивјак",
   "prezime127": "Дивјакиња",
   "prezime128": "Дивјаковић",
   "prezime129": "Дивљак",
   "prezime130": "Дивљаковић",
   "prezime131": "Дивљан",
   "prezime132": "Дивнић",
   "prezime133": "Дивовић",
   "prezime134": "Дивчевић",
   "prezime135": "Дивчић",
   "prezime136": "Дидановић",
   "prezime137": "Дидулица",
   "prezime138": "Диздар",
   "prezime139": "Диздаревић",
   "prezime140": "Дијаматовић",
   "prezime141": "Дикановић",
   "prezime142": "Диклић",
   "prezime143": "Диковић",
   "prezime144": "Дикосављевић",
   "prezime145": "Дилкић",
   "prezime146": "Диманић",
   "prezime147": "Димитријевић",
   "prezime148": "Димитрић",
   "prezime149": "Димић",
   "prezime150": "Димкић",
   "prezime151": "Димковић",
   "prezime152": "Димовић",
   "prezime153": "Димчевић",
   "prezime154": "Димчић",
   "prezime155": "Димшић",
   "prezime156": "Дингарац",
   "prezime157": "Динић",
   "prezime158": "Динкић",
   "prezime159": "Динуловић",
   "prezime160": "Динчић",
   "prezime161": "Дискић",
   "prezime162": "Дичић",
   "prezime163": "Дишевић",
   "prezime164": "Дишљенковић",
   "prezime165": "Дишовић",
   "prezime166": "Дмијовић",
   "prezime167": "Дмитрашиновић",
   "prezime168": "Дмитровић",
   "prezime169": "Добановачки",
   "prezime170": "Добранић",
   "prezime171": "Добрановић",
   "prezime172": "Добратић",
   "prezime173": "Добраш",
   "prezime174": "Добрашиновић",
   "prezime175": "Добре",
   "prezime176": "Добренов",
   "prezime177": "Добреновић",
   "prezime178": "Добречевић",
   "prezime179": "Добривојевић",
   "prezime180": "Добријевић",
   "prezime181": "Добриковић",
   "prezime182": "Добриловић",
   "prezime183": "Добринковић",
   "prezime184": "Добрић",
   "prezime185": "Добрица",
   "prezime186": "Добрицановић",
   "prezime187": "Добричанин",
   "prezime188": "Добричинац",
   "prezime189": "Добричић",
   "prezime190": "Добришеровић",
   "prezime191": "Добрњац",
   "prezime192": "Добровић",
   "prezime193": "Добровоцки",
   "prezime194": "Добродолац",
   "prezime195": "Добројевић",
   "prezime196": "Доброкес",
   "prezime197": "Добромиров",
   "prezime198": "Добромировић",
   "prezime199": "Добросављев",
   "prezime200": "Добросављевић",
   "prezime201": "Доброта",
   "prezime202": "Доведан",
   "prezime203": "Довијанић",
   "prezime204": "Довијарски",
   "prezime205": "Довниковић",
   "prezime206": "Доганџић",
   "prezime207": "Догањић",
   "prezime208": "Додер",
   "prezime209": "Додеровић",
   "prezime210": "Додик",
   "prezime211": "Додић",
   "prezime212": "Додош",
   "prezime213": "Дозет",
   "prezime214": "Дојчиловић",
   "prezime215": "Дојчиновић",
   "prezime216": "Докић",
   "prezime217": "Докманац",
   "prezime218": "Докманов",
   "prezime219": "Докмановић",
   "prezime220": "Докнић",
   "prezime221": "Долаш",
   "prezime222": "Долашевић",
   "prezime223": "Долбочановић",
   "prezime224": "Долинац",
   "prezime225": "Долинић",
   "prezime226": "Доловац",
   "prezime227": "Доловачки",
   "prezime228": "Доловић",
   "prezime229": "Дољанчевић",
   "prezime230": "Домазет",
   "prezime231": "Домановић",
   "prezime232": "Домишевац",
   "prezime233": "Дондур",
   "prezime234": "Доневић",
   "prezime235": "Дончић",
   "prezime236": "Допуђа",
   "prezime237": "Дорић",
   "prezime238": "Доронтић",
   "prezime239": "Дороњски",
   "prezime240": "Дорословац",
   "prezime241": "Дорословачки",
   "prezime242": "Дорошки",
   "prezime243": "Дорошков",
   "prezime244": "Досковић",
   "prezime245": "Достанић",
   "prezime246": "Достић",
   "prezime247": "Дотлић",
   "prezime248": "Дошен",
   "prezime249": "Дошеновић",
   "prezime250": "Дошло",
   "prezime251": "Дошлов",
   "prezime252": "Дравић",
   "prezime253": "Драганић",
   "prezime254": "Драганов",
   "prezime255": "Драгановић",
   "prezime256": "Драгањац",
   "prezime257": "Драгачевац",
   "prezime258": "Драгачевић",
   "prezime259": "Драгаш",
   "prezime260": "Драгашевић",
   "prezime261": "Драгељевић",
   "prezime262": "Драгин",
   "prezime263": "Драгинчић",
   "prezime264": "Драгић",
   "prezime265": "Драгићевић",
   "prezime266": "Драгичевић",
   "prezime267": "Драгишић",
   "prezime268": "Драговачки",
   "prezime269": "Драговић",
   "prezime270": "Драгојевић",
   "prezime271": "Драгојлов",
   "prezime272": "Драгојловић",
   "prezime273": "Драгољевић",
   "prezime274": "Драгољић",
   "prezime275": "Драгомиров",
   "prezime276": "Драгомировић",
   "prezime277": "Драгоњић",
   "prezime278": "Драгосавац",
   "prezime279": "Драгосављевић",
   "prezime280": "Драгославић",
   "prezime281": "Драготић",
   "prezime282": "Драгош",
   "prezime283": "Драгошановић",
   "prezime284": "Драгошев",
   "prezime285": "Драгуловић",
   "prezime286": "Драгуљевић",
   "prezime287": "Драгумило",
   "prezime288": "Драгуновић",
   "prezime289": "Драгутиновић",
   "prezime290": "Драгуцановић",
   "prezime291": "Драгушиновић",
   "prezime292": "Дражевић",
   "prezime293": "Дражета",
   "prezime294": "Дражетин",
   "prezime295": "Дражиловић",
   "prezime296": "Дражин",
   "prezime297": "Дражинац",
   "prezime298": "Дражић",
   "prezime299": "Дражовић",
   "prezime300": "Драјић",
   "prezime301": "Драковац",
   "prezime302": "Драксимовић",
   "prezime303": "Дракула",
   "prezime304": "Дракулић",
   "prezime305": "Драмићанин",
   "prezime306": "Драмлић",
   "prezime307": "Дрангић",
   "prezime308": "Драпшин",
   "prezime309": "Драча",
   "prezime310": "Драшкић",
   "prezime311": "Драшко",
   "prezime312": "Драшковић",
   "prezime313": "Драшовић",
   "prezime314": "Дрваревић",
   "prezime315": "Дрвеница",
   "prezime316": "Дрезга",
   "prezime317": "Дрезгић",
   "prezime318": "Дреновак",
   "prezime319": "Дреноваковић",
   "prezime320": "Дреновац",
   "prezime321": "Дрењанин",
   "prezime322": "Дрецун",
   "prezime323": "Дрешевић",
   "prezime324": "Дринић",
   "prezime325": "Дринчевић",
   "prezime326": "Дринчић",
   "prezime327": "Дрињак",
   "prezime328": "Дрињаковић",
   "prezime329": "Дрљан",
   "prezime330": "Дрљача",
   "prezime331": "Дрманац",
   "prezime332": "Дрндаревић",
   "prezime333": "Дробац",
   "prezime334": "Дробиловић",
   "prezime335": "Дробњак",
   "prezime336": "Дробњаковић",
   "prezime337": "Дроњак",
   "prezime338": "Дружетић",
   "prezime339": "Друлић",
   "prezime340": "Друловић",
   "prezime341": "Дрча",
   "prezime342": "Дубајић",
   "prezime343": "Дубаковић",
   "prezime344": "Дубачкић",
   "prezime345": "Дубичанин",
   "prezime346": "Дубљанин",
   "prezime347": "Дубљевић",
   "prezime348": "Дубовац",
   "prezime349": "Дубовина",
   "prezime350": "Дубоњац",
   "prezime351": "Дубоњић",
   "prezime352": "Дубочанин",
   "prezime353": "Дубравац",
   "prezime354": "Дуброја",
   "prezime355": "Дубурија",
   "prezime356": "Дувњак",
   "prezime357": "Дугалић",
   "prezime358": "Дугић",
   "prezime359": "Дугоња",
   "prezime360": "Дугоњић",
   "prezime361": "Дугошија",
   "prezime362": "Дудварски",
   "prezime363": "Дудић",
   "prezime364": "Дудуковић",
   "prezime365": "Дујаковић",
   "prezime366": "Дујановић",
   "prezime367": "Дујин",
   "prezime368": "Дујковић",
   "prezime369": "Дујовић",
   "prezime370": "Дука",
   "prezime371": "Дукадиновић",
   "prezime372": "Дуканац",
   "prezime373": "Дукатаров",
   "prezime374": "Дукић",
   "prezime375": "Дуковић",
   "prezime376": "Дулановић",
   "prezime377": "Дуликрава",
   "prezime378": "Дуликравић",
   "prezime379": "Дулкановић",
   "prezime380": "Дуловић",
   "prezime381": "Думановић",
   "prezime382": "Думанчевић",
   "prezime383": "Думањић",
   "prezime384": "Думбеловић",
   "prezime385": "Думељић",
   "prezime386": "Думитрашковић",
   "prezime387": "Думитрикић",
   "prezime388": "Думитров",
   "prezime389": "Думнић",
   "prezime390": "Думонић",
   "prezime391": "Дунђерин",
   "prezime392": "Дунђеровић",
   "prezime393": "Дунђерски",
   "prezime394": "Дуновић",
   "prezime395": "Дунчевић",
   "prezime396": "Дунчић",
   "prezime397": "Дуњић",
   "prezime398": "Дупало",
   "prezime399": "Дупљанин",
   "prezime400": "Дупор",
   "prezime401": "Дурбаба",
   "prezime402": "Дурковић",
   "prezime403": "Дурлевић",
   "prezime404": "Дурман",
   "prezime405": "Дуроњић",
   "prezime406": "Дурсун",
   "prezime407": "Дутина",
   "prezime408": "Дуцановић",
   "prezime409": "Дучић",
   "prezime410": "Душанић",
   "prezime411": "Душановић",
   "prezime412": "Душић",
   "prezime413": "Душковић"
 }
]